sputter/__init__.py
sputter/alphabet_trie.py
sputter/anagram.py
sputter/cipher.py
sputter/coincidence.py
sputter/fitness.py
sputter/mung.py
sputter/optimize.py
sputter/py.typed
sputter/spacer.py
sputter/sputter.py
sputter/unweaver.py
sputter/word_features.py
sputter/data/english_quadgrams.txt.gz
sputter/data/english_words_50k.txt.gz
sputter-0.1.5.dist-info/METADATA
sputter-0.1.5.dist-info/WHEEL
sputter-0.1.5.dist-info/entry_points.txt
sputter-0.1.5.dist-info/licenses/LICENSE
sputter-0.1.5.dist-info/RECORD
