Metadata-Version: 2.4
Name: sputter
Version: 0.1.5
Summary: a Statistical PUzzle TexT procEssoR library
Project-URL: Homepage, https://github.com/obijywk/sputter
Project-URL: Documentation, https://obijywk.github.io/sputter/
Project-URL: Repository, https://github.com/obijywk/sputter
Author-email: Matt Gruskin <matthew.gruskin@gmail.com>
License-File: LICENSE
Classifier: Development Status :: 3 - Alpha
Classifier: Intended Audience :: Developers
Classifier: License :: OSI Approved :: MIT License
Classifier: Operating System :: OS Independent
Classifier: Programming Language :: Python
Requires-Python: >=3.12
Requires-Dist: numpy>=2.2.4
Requires-Dist: platformdirs>=4.3.6
Requires-Dist: scipy>=1.15.2
Requires-Dist: typer>=0.15.2
